Workbook
Name NativeTimeline_DATE: #N/A

Sheet Catalogue
A1: PRODUCT ID | B1: PRODUCT | C1: CATEGORY | D1: UOM | E1: BUYING PRICE | F1: SELLING PRICE
A2: P1001 | B2: Dove Soap | C2: Personal Care | D2: 100g bar | E2: 98 | F2: 129.36
A3: P1002 | B3: Colgate Toothpaste | C3: Personal Care | D3: 150g tube | E3: 105 | F3: 117.6
A4: P1003 | B4: Lifebuoy Handwash | C4: Personal Care | D4: 200ml bottle | E4: 44 | F4: 50.16
A5: P1004 | B5: Nivea Body Lotion | C5: Personal Care | D5: 400ml bottle | E5: 71 | F5: 80.23
A6: P1005 | B6: Gillette Shaving Foam | C6: Personal Care | D6: 200g can | E6: 133 | F6: 187.53
A7: P1006 | B7: Pantene Shampoo | C7: Personal Care | D7: 340ml bottle | E7: 124 | F7: 204.6
A8: P1007 | B8: Dettol Antiseptic Liquid | C8: Personal Care | D8: 250ml bottle | E8: 10 | F8: 11.2
A9: P1008 | B9: Himalaya Face Wash | C9: Personal Care | D9: 150ml tube | E9: 16 | F9: 17.6
A10: P1009 | B10: Vaseline Lip Care | C10: Personal Care | D10: 10g stick | E10: 10 | F10: 13.5
A11: P1010 | B11: Johnson’s Baby Powder | C11: Personal Care | D11: 500g bottle | E11: 123 | F11: 179.58
A12: P2001 | B12: Coca-Cola Can | C12: Beverages | D12: 330ml can | E12: 136 | F12: 179.52
A13: P2002 | B13: Pepsi Bottle | C13: Beverages | D13: 500ml bottle | E13: 12 | F13: 13.44
... A51: P5010 | B51: Wet Wipes - Himalaya | C51: Paper & Essentials | D51: 20 wipes | E51: 12 | F51: 17.52

Sheet Sheet7
A3: Row Labels | B3: Sum of SELLING VALUE | D3: Row Labels | E3: Sum of SELLING VALUE | G3: Row Labels | H3: Sum of SELLING VALUE | K3: Row Labels | L3: Sum of SELLING VALUE | M3: Sum of PROFIT | R3: Row Labels | S3: Sum of SELLING VALUE | W3: Row Labels | X3: Sum of SELLING VALUE | AA3: Row Labels | AB3: Sum of QTY
A4: Coca-Cola Can | B4: 12256.44 | D4: Beverages | E4: 100233.95 | G4: Jan | H4: 55973.89 | K4: Jan | L4: 29870.46 | M4: 6218.46 | R4: Cash | S4: 252031.48 | W4: Online | X4: 154019.16 | AA4: Online | AB4: 1576
A5: Dove Soap | B5: 11749.5 | D5: Household Cleaning | E5: 80011.81 | G5: Feb | H5: 49485.85 | K5: Feb | L5: 20204.85 | M5: 4160.85 | R5: Online | S5: 183788.96 | W5: Retail Sales | X5: 95499.7 | AA5: Retail Sales | AB5: 1012
A6: Minute Maid Pulpy | B6: 12760.37 | D6: Packaged Foods | E6: 86925.65 | G6: Mar | H6: 37519.15 | K6: Mar | L6: 35360.17 | M6: 8818.17 | R6: Grand Total | S6: 435820.44 | W6: Wholesaler | X6: 186301.58 | AA6: Wholesaler | AB6: 1982
A7: MTR Ready Curry | B7: 12392.23 | D7: Paper & Essentials | E7: 78653.68 | G7: Apr | H7: 21968.94 | K7: Apr | L7: 21968.94 | M7: 5192.94 | W7: Grand Total | X7: 435820.44 | AA7: Grand Total | AB7: 4570
A8: Nivea Body Lotion | B8: 12863.12 | D8: Personal Care | E8: 89995.35 | G8: May | H8: 31424.58 | K8: May | L8: 31424.58 | M8: 4949.58
A9: Real Mixed Fruit Juice | B9: 12812.35 | D9: Grand Total | E9: 435820.44 | G9: Jun | H9: 33370.03 | K9: Jun | L9: 33370.03 | M9: 9492.03
A10: Surf Excel Detergent | B10: 12052.58 | G10: Jul | H10: 32734.8 | K10: Jul | L10: 32734.8 | M10: 7602.8
A11: Top Ramen | B11: 11530.43 | G11: Aug | H11: 33709.95 | K11: Aug | L11: 33709.95 | M11: 7122.95
A12: Tropicana Orange Juice | B12: 12233.76 | G12: Sep | H12: 38926.74 | K12: Sep | L12: 38926.74 | M12: 10702.74
A13: Yippee Noodles | B13: 11598.76 | G13: Oct | H13: 34754.9 | K13: Oct | L13: 34754.9 | M13: 7623.9
A14: Grand Total | B14: 122249.54 | G14: Nov | H14: 31789.88 | K14: Nov | L14: 31789.88 | M14: 6000.88
G15: Dec | H15: 34161.73 | K15: Dec | L15: 34161.73 | M15: 8472.73
G16: Grand Total | H16: 435820.44 | K16: Grand Total | L16: 378277.03 | M16: 86358.03

Sheet Sales Report
A1: DATE | B1: PRODUCT ID | C1: QTY | D1: SALES TYPE | E1: PAYMENT MODE | F1: BUYING PRICE | G1: SELLING PRICE | H1: COST VALUE | I1: SELLING VALUE | J1: PROFIT | K1: PRODUCT | L1: MONTH | M1: CATEGORY
A2: 45292 | B2: P3004 | C2: 10 | D2: Wholesaler | E2: Online | F2: =VLOOKUP(B2,Catalogue!$A$1:$F$51,5,FALSE) -> 136 | G2: =VLOOKUP(B2,Catalogue!$A$1:$F$51,6,FALSE) -> 153.68 | H2: =C2*F2 -> 1360 | I2: =C2*G2 -> 1536.8 | J2: =I2-H2 -> 176.8 | K2: {=Catalogue!B2:B51} -> Dove Soap | L2: =TEXT(A2,"mmm") -> Jan | M2: {=Catalogue!C2:C51} -> Personal Care
A3: 45293 | B3: P5001 | C3: 2 | D3: Online | E3: Cash | F3: =VLOOKUP(B3,Catalogue!$A$1:$F$51,5,FALSE) -> 44 | G3: =VLOOKUP(B3,Catalogue!$A$1:$F$51,6,FALSE) -> 58.08 | H3: =C3*F3 -> 88 | I3: =C3*G3 -> 116.16 | J3: =I3-H3 -> 28.16 | K3: Colgate Toothpaste | L3: =TEXT(A3,"mmm") -> Jan | M3: Personal Care
A4: 45294 | B4: P3003 | C4: 2 | D4: Retail Sales | E4: Cash | F4: =VLOOKUP(B4,Catalogue!$A$1:$F$51,5,FALSE) -> 123 | G4: =VLOOKUP(B4,Catalogue!$A$1:$F$51,6,FALSE) -> 140.22 | H4: =C4*F4 -> 246 | I4: =C4*G4 -> 280.44 | J4: =I4-H4 -> 34.44 | K4: Lifebuoy Handwash | L4: =TEXT(A4,"mmm") -> Jan | M4: Personal Care
A5: 45295 | B5: P5010 | C5: 11 | D5: Retail Sales | E5: Online | F5: =VLOOKUP(B5,Catalogue!$A$1:$F$51,5,FALSE) -> 12 | G5: =VLOOKUP(B5,Catalogue!$A$1:$F$51,6,FALSE) -> 17.52 | H5: =C5*F5 -> 132 | I5: =C5*G5 -> 192.72 | J5: =I5-H5 -> 60.72 | K5: Nivea Body Lotion | L5: =TEXT(A5,"mmm") -> Jan | M5: Personal Care
A6: 45296 | B6: P5001 | C6: 18 | D6: Online | E6: Cash | F6: =VLOOKUP(B6,Catalogue!$A$1:$F$51,5,FALSE) -> 44 | G6: =VLOOKUP(B6,Catalogue!$A$1:$F$51,6,FALSE) -> 58.08 | H6: =C6*F6 -> 792 | I6: =C6*G6 -> 1045.44 | J6: =I6-H6 -> 253.44 | K6: Gillette Shaving Foam | L6: =TEXT(A6,"mmm") -> Jan | M6: Personal Care
A7: 45297 | B7: P1007 | C7: 10 | D7: Wholesaler | E7: Online | F7: =VLOOKUP(B7,Catalogue!$A$1:$F$51,5,FALSE) -> 10 | G7: =VLOOKUP(B7,Catalogue!$A$1:$F$51,6,FALSE) -> 11.2 | H7: =C7*F7 -> 100 | I7: =C7*G7 -> 112 | J7: =I7-H7 -> 12 | K7: Pantene Shampoo | L7: =TEXT(A7,"mmm") -> Jan | M7: Personal Care
A8: 45298 | B8: P5006 | C8: 14 | D8: Wholesaler | E8: Cash | F8: =VLOOKUP(B8,Catalogue!$A$1:$F$51,5,FALSE) -> 16 | G8: =VLOOKUP(B8,Catalogue!$A$1:$F$51,6,FALSE) -> 26.4 | H8: =C8*F8 -> 224 | I8: =C8*G8 -> 369.6 | J8: =I8-H8 -> 145.6 | K8: Dettol Antiseptic Liquid | L8: =TEXT(A8,"mmm") -> Jan | M8: Personal Care
A9: 45299 | B9: P3008 | C9: 10 | D9: Online | E9: Online | F9: =VLOOKUP(B9,Catalogue!$A$1:$F$51,5,FALSE) -> 44 | G9: =VLOOKUP(B9,Catalogue!$A$1:$F$51,6,FALSE) -> 48.4 | H9: =C9*F9 -> 440 | I9: =C9*G9 -> 484 | J9: =I9-H9 -> 44 | K9: Himalaya Face Wash | L9: =TEXT(A9,"mmm") -> Jan | M9: Personal Care
A10: 45300 | B10: P4001 | C10: 16 | D10: Wholesaler | E10: Cash | F10: =VLOOKUP(B10,Catalogue!$A$1:$F$51,5,FALSE) -> 124 | G10: =VLOOKUP(B10,Catalogue!$A$1:$F$51,6,FALSE) -> 163.68 | H10: =C10*F10 -> 1984 | I10: =C10*G10 -> 2618.88 | J10: =I10-H10 -> 634.88 | K10: Vaseline Lip Care | L10: =TEXT(A10,"mmm") -> Jan | M10: Personal Care
A11: 45301 | B11: P4004 | C11: 14 | D11: Wholesaler | E11: Cash | F11: =VLOOKUP(B11,Catalogue!$A$1:$F$51,5,FALSE) -> 10 | G11: =VLOOKUP(B11,Catalogue!$A$1:$F$51,6,FALSE) -> 11.3 | H11: =C11*F11 -> 140 | I11: =C11*G11 -> 158.2 | J11: =I11-H11 -> 18.2 | K11: Johnson’s Baby Powder | L11: =TEXT(A11,"mmm") -> Jan | M11: Personal Care
A12: 45302 | B12: P3003 | C12: 17 | D12: Online | E12: Online | F12: =VLOOKUP(B12,Catalogue!$A$1:$F$51,5,FALSE) -> 123 | G12: =VLOOKUP(B12,Catalogue!$A$1:$F$51,6,FALSE) -> 140.22 | H12: =C12*F12 -> 2091 | I12: =C12*G12 -> 2383.74 | J12: =I12-H12 -> 292.74 | K12: Coca-Cola Can | L12: =TEXT(A12,"mmm") -> Jan | M12: Beverages
A13: 45303 | B13: P2002 | C13: 10 | D13: Retail Sales | E13: Cash | F13: =VLOOKUP(B13,Catalogue!$A$1:$F$51,5,FALSE) -> 12 | G13: =VLOOKUP(B13,Catalogue!$A$1:$F$51,6,FALSE) -> 13.44 | H13: =C13*F13 -> 120 | I13: =C13*G13 -> 134.4 | J13: =I13-H13 -> 14.4 | K13: Pepsi Bottle | L13: =TEXT(A13,"mmm") -> Jan | M13: Beverages
A14: 45304 | B14: P5009 | C14: 8 | D14: Retail Sales | E14: Cash | F14: =VLOOKUP(B14,Catalogue!$A$1:$F$51,5,FALSE) -> 136 | G14: =VLOOKUP(B14,Catalogue!$A$1:$F$51,6,FALSE) -> 183.6 | H14: =C14*F14 -> 1088 | I14: =C14*G14 -> 1468.8 | J14: =I14-H14 -> 380.8 | K14: Red Bull | L14: =TEXT(A14,"mmm") -> Jan | M14: Beverages
... A51: 45341 | B51: P3002 | C51: 8 | D51: Online | E51: Cash | F51: =VLOOKUP(B51,Catalogue!$A$1:$F$51,5,FALSE) -> 10 | G51: =VLOOKUP(B51,Catalogue!$A$1:$F$51,6,FALSE) -> 11.2 | H51: =C51*F51 -> 80 | I51: =C51*G51 -> 89.6 | J51: =I51-H51 -> 9.6 | K51: Wet Wipes - Himalaya | L51: =TEXT(A51,"mmm") -> Feb | M51: Paper & Essentials
A52: 45342 | B52: P4005 | C52: 5 | D52: Wholesaler | E52: Online | F52: =VLOOKUP(B52,Catalogue!$A$1:$F$51,5,FALSE) -> 123 | G52: =VLOOKUP(B52,Catalogue!$A$1:$F$51,6,FALSE) -> 173.43 | H52: =C52*F52 -> 615 | I52: =C52*G52 -> 867.15 | J52: =I52-H52 -> 252.15 | K52: {=Catalogue!B2:B51} -> Dove Soap | L52: =TEXT(A52,"mmm") -> Feb | M52: {=Catalogue!C2:C51} -> Personal Care
A53: 45343 | B53: P1008 | C53: 20 | D53: Wholesaler | E53: Cash | F53: =VLOOKUP(B53,Catalogue!$A$1:$F$51,5,FALSE) -> 16 | G53: =VLOOKUP(B53,Catalogue!$A$1:$F$51,6,FALSE) -> 17.6 | H53: =C53*F53 -> 320 | I53: =C53*G53 -> 352 | J53: =I53-H53 -> 32 | K53: Colgate Toothpaste | L53: =TEXT(A53,"mmm") -> Feb | M53: Personal Care
A54: 45344 | B54: P3008 | C54: 10 | D54: Online | E54: Cash | F54: =VLOOKUP(B54,Catalogue!$A$1:$F$51,5,FALSE) -> 44 | G54: =VLOOKUP(B54,Catalogue!$A$1:$F$51,6,FALSE) -> 48.4 | H54: =C54*F54 -> 440 | I54: =C54*G54 -> 484 | J54: =I54-H54 -> 44 | K54: Lifebuoy Handwash | L54: =TEXT(A54,"mmm") -> Feb | M54: Personal Care
A55: 45345 | B55: P5006 | C55: 12 | D55: Wholesaler | E55: Online | F55: =VLOOKUP(B55,Catalogue!$A$1:$F$51,5,FALSE) -> 16 | G55: =VLOOKUP(B55,Catalogue!$A$1:$F$51,6,FALSE) -> 26.4 | H55: =C55*F55 -> 192 | I55: =C55*G55 -> 316.8 | J55: =I55-H55 -> 124.8 | K55: Nivea Body Lotion | L55: =TEXT(A55,"mmm") -> Feb | M55: Personal Care
A56: 45346 | B56: P5010 | C56: 5 | D56: Wholesaler | E56: Cash | F56: =VLOOKUP(B56,Catalogue!$A$1:$F$51,5,FALSE) -> 12 | G56: =VLOOKUP(B56,Catalogue!$A$1:$F$51,6,FALSE) -> 17.52 | H56: =C56*F56 -> 60 | I56: =C56*G56 -> 87.6 | J56: =I56-H56 -> 27.6 | K56: Gillette Shaving Foam | L56: =TEXT(A56,"mmm") -> Feb | M56: Personal Care
A57: 45347 | B57: P5006 | C57: 3 | D57: Online | E57: Online | F57: =VLOOKUP(B57,Catalogue!$A$1:$F$51,5,FALSE) -> 16 | G57: =VLOOKUP(B57,Catalogue!$A$1:$F$51,6,FALSE) -> 26.4 | H57: =C57*F57 -> 48 | I57: =C57*G57 -> 79.2 | J57: =I57-H57 -> 31.2 | K57: Pantene Shampoo | L57: =TEXT(A57,"mmm") -> Feb | M57: Personal Care
A58: 45348 | B58: P5005 | C58: 8 | D58: Retail Sales | E58: Cash | F58: =VLOOKUP(B58,Catalogue!$A$1:$F$51,5,FALSE) -> 10 | G58: =VLOOKUP(B58,Catalogue!$A$1:$F$51,6,FALSE) -> 14.1 | H58: =C58*F58 -> 80 | I58: =C58*G58 -> 112.8 | J58: =I58-H58 -> 32.8 | K58: Dettol Antiseptic Liquid | L58: =TEXT(A58,"mmm") -> Feb | M58: Personal Care
A59: 45349 | B59: P3004 | C59: 7 | D59: Retail Sales | E59: Online | F59: =VLOOKUP(B59,Catalogue!$A$1:$F$51,5,FALSE) -> 136 | G59: =VLOOKUP(B59,Catalogue!$A$1:$F$51,6,FALSE) -> 153.68 | H59: =C59*F59 -> 952 | I59: =C59*G59 -> 1075.76 | J59: =I59-H59 -> 123.76 | K59: Himalaya Face Wash | L59: =TEXT(A59,"mmm") -> Feb | M59: Personal Care
A60: 45350 | B60: P3001 | C60: 6 | D60: Online | E60: Cash | F60: =VLOOKUP(B60,Catalogue!$A$1:$F$51,5,FALSE) -> 16 | G60: =VLOOKUP(B60,Catalogue!$A$1:$F$51,6,FALSE) -> 21.12 | H60: =C60*F60 -> 96 | I60: =C60*G60 -> 126.72 | J60: =I60-H60 -> 30.72 | K60: Vaseline Lip Care | L60: =TEXT(A60,"mmm") -> Feb | M60: Personal Care
A61: 45351 | B61: P5008 | C61: 1 | D61: Wholesaler | E61: Cash | F61: =VLOOKUP(B61,Catalogue!$A$1:$F$51,5,FALSE) -> 123 | G61: =VLOOKUP(B61,Catalogue!$A$1:$F$51,6,FALSE) -> 135.3 | H61: =C61*F61 -> 123 | I61: =C61*G61 -> 135.3 | J61: =I61-H61 -> 12.3 | K61: Johnson’s Baby Powder | L61: =TEXT(A61,"mmm") -> Feb | M61: Personal Care
A62: 45352 | B62: P3009 | C62: 14 | D62: Wholesaler | E62: Online | F62: =VLOOKUP(B62,Catalogue!$A$1:$F$51,5,FALSE) -> 71 | G62: =VLOOKUP(B62,Catalogue!$A$1:$F$51,6,FALSE) -> 95.85 | H62: =C62*F62 -> 994 | I62: =C62*G62 -> 1341.9 | J62: =I62-H62 -> 347.9 | K62: Coca-Cola Can | L62: =TEXT(A62,"mmm") -> Mar | M62: Beverages
A63: 45353 | B63: P3009 | C63: 20 | D63: Online | E63: Cash | F63: =VLOOKUP(B63,Catalogue!$A$1:$F$51,5,FALSE) -> 71 | G63: =VLOOKUP(B63,Catalogue!$A$1:$F$51,6,FALSE) -> 95.85 | H63: =C63*F63 -> 1420 | I63: =C63*G63 -> 1917 | J63: =I63-H63 -> 497 | K63: Pepsi Bottle | L63: =TEXT(A63,"mmm") -> Mar | M63: Beverages
A64: 45354 | B64: P3007 | C64: 13 | D64: Wholesaler | E64: Cash | F64: =VLOOKUP(B64,Catalogue!$A$1:$F$51,5,FALSE) -> 105 | G64: =VLOOKUP(B64,Catalogue!$A$1:$F$51,6,FALSE) -> 117.6 | H64: =C64*F64 -> 1365 | I64: =C64*G64 -> 1528.8 | J64: =I64-H64 -> 163.8 | K64: Red Bull | L64: =TEXT(A64,"mmm") -> Mar | M64: Beverages
... A101: 45391 | B101: P1010 | C101: 6 | D101: Wholesaler | E101: Cash | F101: =VLOOKUP(B101,Catalogue!$A$1:$F$51,5,FALSE) -> 123 | G101: =VLOOKUP(B101,Catalogue!$A$1:$F$51,6,FALSE) -> 179.58 | H101: =C101*F101 -> 738 | I101: =C101*G101 -> 1077.48 | J101: =I101-H101 -> 339.48 | K101: Wet Wipes - Himalaya | L101: =TEXT(A101,"mmm") -> Apr | M101: Paper & Essentials
A102: 45392 | B102: P1001 | C102: 4 | D102: Online | E102: Online | F102: =VLOOKUP(B102,Catalogue!$A$1:$F$51,5,FALSE) -> 98 | G102: =VLOOKUP(B102,Catalogue!$A$1:$F$51,6,FALSE) -> 129.36 | H102: =C102*F102 -> 392 | I102: =C102*G102 -> 517.44 | J102: =I102-H102 -> 125.44 | K102: {=Catalogue!B2:B51} -> Dove Soap | L102: =TEXT(A102,"mmm") -> Apr | M102: {=Catalogue!C2:C51} -> Personal Care
A103: 45393 | B103: P5009 | C103: 9 | D103: Retail Sales | E103: Cash | F103: =VLOOKUP(B103,Catalogue!$A$1:$F$51,5,FALSE) -> 136 | G103: =VLOOKUP(B103,Catalogue!$A$1:$F$51,6,FALSE) -> 183.6 | H103: =C103*F103 -> 1224 | I103: =C103*G103 -> 1652.4 | J103: =I103-H103 -> 428.4 | K103: Colgate Toothpaste | L103: =TEXT(A103,"mmm") -> Apr | M103: Personal Care
A104: 45394 | B104: P1008 | C104: 9 | D104: Retail Sales | E104: Cash | F104: =VLOOKUP(B104,Catalogue!$A$1:$F$51,5,FALSE) -> 16 | G104: =VLOOKUP(B104,Catalogue!$A$1:$F$51,6,FALSE) -> 17.6 | H104: =C104*F104 -> 144 | I104: =C104*G104 -> 158.4 | J104: =I104-H104 -> 14.4 | K104: Lifebuoy Handwash | L104: =TEXT(A104,"mmm") -> Apr | M104: Personal Care
A105: 45395 | B105: P3005 | C105: 2 | D105: Online | E105: Online | F105: =VLOOKUP(B105,Catalogue!$A$1:$F$51,5,FALSE) -> 12 | G105: =VLOOKUP(B105,Catalogue!$A$1:$F$51,6,FALSE) -> 16.92 | H105: =C105*F105 -> 24 | I105: =C105*G105 -> 33.84 | J105: =I105-H105 -> 9.84 | K105: Nivea Body Lotion | L105: =TEXT(A105,"mmm") -> Apr | M105: Personal Care
A106: 45396 | B106: P3005 | C106: 15 | D106: Wholesaler | E106: Cash | F106: =VLOOKUP(B106,Catalogue!$A$1:$F$51,5,FALSE) -> 12 | G106: =VLOOKUP(B106,Catalogue!$A$1:$F$51,6,FALSE) -> 16.92 | H106: =C106*F106 -> 180 | I106: =C106*G106 -> 253.8 | J106: =I106-H106 -> 73.8 | K106: Gillette Shaving Foam | L106: =TEXT(A106,"mmm") -> Apr | M106: Personal Care
A107: 45397 | B107: P2006 | C107: 3 | D107: Wholesaler | E107: Online | F107: =VLOOKUP(B107,Catalogue!$A$1:$F$51,5,FALSE) -> 44 | G107: =VLOOKUP(B107,Catalogue!$A$1:$F$51,6,FALSE) -> 72.6 | H107: =C107*F107 -> 132 | I107: =C107*G107 -> 217.8 | J107: =I107-H107 -> 85.8 | K107: Pantene Shampoo | L107: =TEXT(A107,"mmm") -> Apr | M107: Personal Care
A108: 45398 | B108: P2006 | C108: 14 | D108: Online | E108: Cash | F108: =VLOOKUP(B108,Catalogue!$A$1:$F$51,5,FALSE) -> 44 | G108: =VLOOKUP(B108,Catalogue!$A$1:$F$51,6,FALSE) -> 72.6 | H108: =C108*F108 -> 616 | I108: =C108*G108 -> 1016.4 | J108: =I108-H108 -> 400.4 | K108: Dettol Antiseptic Liquid | L108: =TEXT(A108,"mmm") -> Apr | M108: Personal Care
A109: 45399 | B109: P5009 | C109: 3 | D109: Wholesaler | E109: Online | F109: =VLOOKUP(B109,Catalogue!$A$1:$F$51,5,FALSE) -> 136 | G109: =VLOOKUP(B109,Catalogue!$A$1:$F$51,6,FALSE) -> 183.6 | H109: =C109*F109 -> 408 | I109: =C109*G109 -> 550.8 | J109: =I109-H109 -> 142.8 | K109: Himalaya Face Wash | L109: =TEXT(A109,"mmm") -> Apr | M109: Personal Care
A110: 45400 | B110: P5010 | C110: 19 | D110: Wholesaler | E110: Cash | F110: =VLOOKUP(B110,Catalogue!$A$1:$F$51,5,FALSE) -> 12 | G110: =VLOOKUP(B110,Catalogue!$A$1:$F$51,6,FALSE) -> 17.52 | H110: =C110*F110 -> 228 | I110: =C110*G110 -> 332.88 | J110: =I110-H110 -> 104.88 | K110: Vaseline Lip Care | L110: =TEXT(A110,"mmm") -> Apr | M110: Personal Care
A111: 45401 | B111: P1005 | C111: 2 | D111: Online | E111: Cash | F111: =VLOOKUP(B111,Catalogue!$A$1:$F$51,5,FALSE) -> 133 | G111: =VLOOKUP(B111,Catalogue!$A$1:$F$51,6,FALSE) -> 187.53 | H111: =C111*F111 -> 266 | I111: =C111*G111 -> 375.06 | J111: =I111-H111 -> 109.06 | K111: Johnson’s Baby Powder | L111: =TEXT(A111,"mmm") -> Apr | M111: Personal Care
A112: 45402 | B112: P2001 | C112: 8 | D112: Retail Sales | E112: Online | F112: =VLOOKUP(B112,Catalogue!$A$1:$F$51,5,FALSE) -> 136 | G112: =VLOOKUP(B112,Catalogue!$A$1:$F$51,6,FALSE) -> 179.52 | H112: =C112*F112 -> 1088 | I112: =C112*G112 -> 1436.16 | J112: =I112-H112 -> 348.16 | K112: Coca-Cola Can | L112: =TEXT(A112,"mmm") -> Apr | M112: Beverages
A113: 45403 | B113: P5008 | C113: 10 | D113: Retail Sales | E113: Cash | F113: =VLOOKUP(B113,Catalogue!$A$1:$F$51,5,FALSE) -> 123 | G113: =VLOOKUP(B113,Catalogue!$A$1:$F$51,6,FALSE) -> 135.3 | H113: =C113*F113 -> 1230 | I113: =C113*G113 -> 1353 | J113: =I113-H113 -> 123 | K113: Pepsi Bottle | L113: =TEXT(A113,"mmm") -> Apr | M113: Beverages
A114: 45404 | B114: P3008 | C114: 12 | D114: Online | E114: Cash | F114: =VLOOKUP(B114,Catalogue!$A$1:$F$51,5,FALSE) -> 44 | G114: =VLOOKUP(B114,Catalogue!$A$1:$F$51,6,FALSE) -> 48.4 | H114: =C114*F114 -> 528 | I114: =C114*G114 -> 580.8 | J114: =I114-H114 -> 52.8 | K114: Red Bull | L114: =TEXT(A114,"mmm") -> Apr | M114: Beverages
... A151: 45441 | B151: P3004 | C151: 10 | D151: Wholesaler | E151: Cash | F151: =VLOOKUP(B151,Catalogue!$A$1:$F$51,5,FALSE) -> 136 | G151: =VLOOKUP(B151,Catalogue!$A$1:$F$51,6,FALSE) -> 153.68 | H151: =C151*F151 -> 1360 | I151: =C151*G151 -> 1536.8 | J151: =I151-H151 -> 176.8 | K151: Wet Wipes - Himalaya | L151: =TEXT(A151,"mmm") -> May | M151: Paper & Essentials
A152: 45442 | B152: P2003 | C152: 19 | D152: Wholesaler | E152: Online | F152: =VLOOKUP(B152,Catalogue!$A$1:$F$51,5,FALSE) -> 63 | G152: =VLOOKUP(B152,Catalogue!$A$1:$F$51,6,FALSE) -> 71.82 | H152: =C152*F152 -> 1197 | I152: =C152*G152 -> 1364.58 | J152: =I152-H152 -> 167.58 | K152: {=Catalogue!B2:B51} -> Dove Soap | L152: =TEXT(A152,"mmm") -> May | M152: {=Catalogue!C2:C51} -> Personal Care
A153: 45443 | B153: P5007 | C153: 1 | D153: Online | E153: Cash | F153: =VLOOKUP(B153,Catalogue!$A$1:$F$51,5,FALSE) -> 10 | G153: =VLOOKUP(B153,Catalogue!$A$1:$F$51,6,FALSE) -> 11.2 | H153: =C153*F153 -> 10 | I153: =C153*G153 -> 11.2 | J153: =I153-H153 -> 1.2 | K153: Colgate Toothpaste | L153: =TEXT(A153,"mmm") -> May | M153: Personal Care
A154: 45444 | B154: P1004 | C154: 4 | D154: Wholesaler | E154: Cash | F154: =VLOOKUP(B154,Catalogue!$A$1:$F$51,5,FALSE) -> 71 | G154: =VLOOKUP(B154,Catalogue!$A$1:$F$51,6,FALSE) -> 80.23 | H154: =C154*F154 -> 284 | I154: =C154*G154 -> 320.92 | J154: =I154-H154 -> 36.92 | K154: Lifebuoy Handwash | L154: =TEXT(A154,"mmm") -> Jun | M154: Personal Care
A155: 45445 | B155: P5008 | C155: 17 | D155: Wholesaler | E155: Online | F155: =VLOOKUP(B155,Catalogue!$A$1:$F$51,5,FALSE) -> 123 | G155: =VLOOKUP(B155,Catalogue!$A$1:$F$51,6,FALSE) -> 135.3 | H155: =C155*F155 -> 2091 | I155: =C155*G155 -> 2300.1 | J155: =I155-H155 -> 209.1 | K155: Nivea Body Lotion | L155: =TEXT(A155,"mmm") -> Jun | M155: Personal Care
A156: 45446 | B156: P2007 | C156: 7 | D156: Online | E156: Cash | F156: =VLOOKUP(B156,Catalogue!$A$1:$F$51,5,FALSE) -> 71 | G156: =VLOOKUP(B156,Catalogue!$A$1:$F$51,6,FALSE) -> 79.52 | H156: =C156*F156 -> 497 | I156: =C156*G156 -> 556.64 | J156: =I156-H156 -> 59.64 | K156: Gillette Shaving Foam | L156: =TEXT(A156,"mmm") -> Jun | M156: Personal Care
A157: 45447 | B157: P5001 | C157: 18 | D157: Retail Sales | E157: Online | F157: =VLOOKUP(B157,Catalogue!$A$1:$F$51,5,FALSE) -> 44 | G157: =VLOOKUP(B157,Catalogue!$A$1:$F$51,6,FALSE) -> 58.08 | H157: =C157*F157 -> 792 | I157: =C157*G157 -> 1045.44 | J157: =I157-H157 -> 253.44 | K157: Pantene Shampoo | L157: =TEXT(A157,"mmm") -> Jun | M157: Personal Care
A158: 45448 | B158: P1010 | C158: 6 | D158: Retail Sales | E158: Cash | F158: =VLOOKUP(B158,Catalogue!$A$1:$F$51,5,FALSE) -> 123 | G158: =VLOOKUP(B158,Catalogue!$A$1:$F$51,6,FALSE) -> 179.58 | H158: =C158*F158 -> 738 | I158: =C158*G158 -> 1077.48 | J158: =I158-H158 -> 339.48 | K158: Dettol Antiseptic Liquid | L158: =TEXT(A158,"mmm") -> Jun | M158: Personal Care
A159: 45449 | B159: P2001 | C159: 11 | D159: Online | E159: Online | F159: =VLOOKUP(B159,Catalogue!$A$1:$F$51,5,FALSE) -> 136 | G159: =VLOOKUP(B159,Catalogue!$A$1:$F$51,6,FALSE) -> 179.52 | H159: =C159*F159 -> 1496 | I159: =C159*G159 -> 1974.72 | J159: =I159-H159 -> 478.72 | K159: Himalaya Face Wash | L159: =TEXT(A159,"mmm") -> Jun | M159: Personal Care
A160: 45450 | B160: P4003 | C160: 9 | D160: Wholesaler | E160: Cash | F160: =VLOOKUP(B160,Catalogue!$A$1:$F$51,5,FALSE) -> 16 | G160: =VLOOKUP(B160,Catalogue!$A$1:$F$51,6,FALSE) -> 18.24 | H160: =C160*F160 -> 144 | I160: =C160*G160 -> 164.16 | J160: =I160-H160 -> 20.16 | K160: Vaseline Lip Care | L160: =TEXT(A160,"mmm") -> Jun | M160: Personal Care
A161: 45451 | B161: P1001 | C161: 9 | D161: Wholesaler | E161: Cash | F161: =VLOOKUP(B161,Catalogue!$A$1:$F$51,5,FALSE) -> 98 | G161: =VLOOKUP(B161,Catalogue!$A$1:$F$51,6,FALSE) -> 129.36 | H161: =C161*F161 -> 882 | I161: =C161*G161 -> 1164.24 | J161: =I161-H161 -> 282.24 | K161: Johnson’s Baby Powder | L161: =TEXT(A161,"mmm") -> Jun | M161: Personal Care
A162: 45452 | B162: P3006 | C162: 11 | D162: Online | E162: Online | F162: =VLOOKUP(B162,Catalogue!$A$1:$F$51,5,FALSE) -> 98 | G162: =VLOOKUP(B162,Catalogue!$A$1:$F$51,6,FALSE) -> 161.7 | H162: =C162*F162 -> 1078 | I162: =C162*G162 -> 1778.7 | J162: =I162-H162 -> 700.7 | K162: Coca-Cola Can | L162: =TEXT(A162,"mmm") -> Jun | M162: Beverages
A163: 45453 | B163: P1004 | C163: 15 | D163: Wholesaler | E163: Cash | F163: =VLOOKUP(B163,Catalogue!$A$1:$F$51,5,FALSE) -> 71 | G163: =VLOOKUP(B163,Catalogue!$A$1:$F$51,6,FALSE) -> 80.23 | H163: =C163*F163 -> 1065 | I163: =C163*G163 -> 1203.45 | J163: =I163-H163 -> 138.45 | K163: Pepsi Bottle | L163: =TEXT(A163,"mmm") -> Jun | M163: Beverages
A164: 45454 | B164: P4002 | C164: 5 | D164: Wholesaler | E164: Cash | F164: =VLOOKUP(B164,Catalogue!$A$1:$F$51,5,FALSE) -> 10 | G164: =VLOOKUP(B164,Catalogue!$A$1:$F$51,6,FALSE) -> 11.2 | H164: =C164*F164 -> 50 | I164: =C164*G164 -> 56 | J164: =I164-H164 -> 6 | K164: Red Bull | L164: =TEXT(A164,"mmm") -> Jun | M164: Beverages
... A201: 45491 | B201: P2006 | C201: 5 | D201: Online | E201: Cash | F201: =VLOOKUP(B201,Catalogue!$A$1:$F$51,5,FALSE) -> 44 | G201: =VLOOKUP(B201,Catalogue!$A$1:$F$51,6,FALSE) -> 72.6 | H201: =C201*F201 -> 220 | I201: =C201*G201 -> 363 | J201: =I201-H201 -> 143 | K201: Wet Wipes - Himalaya | L201: =TEXT(A201,"mmm") -> Jul | M201: Paper & Essentials
A202: 45492 | B202: P5010 | C202: 13 | D202: Retail Sales | E202: Online | F202: =VLOOKUP(B202,Catalogue!$A$1:$F$51,5,FALSE) -> 12 | G202: =VLOOKUP(B202,Catalogue!$A$1:$F$51,6,FALSE) -> 17.52 | H202: =C202*F202 -> 156 | I202: =C202*G202 -> 227.76 | J202: =I202-H202 -> 71.76 | K202: {=Catalogue!B2:B51} -> Dove Soap | L202: =TEXT(A202,"mmm") -> Jul | M202: {=Catalogue!C2:C51} -> Personal Care
A203: 45493 | B203: P1002 | C203: 17 | D203: Retail Sales | E203: Cash | F203: =VLOOKUP(B203,Catalogue!$A$1:$F$51,5,FALSE) -> 105 | G203: =VLOOKUP(B203,Catalogue!$A$1:$F$51,6,FALSE) -> 117.6 | H203: =C203*F203 -> 1785 | I203: =C203*G203 -> 1999.2 | J203: =I203-H203 -> 214.2 | K203: Colgate Toothpaste | L203: =TEXT(A203,"mmm") -> Jul | M203: Personal Care
A204: 45494 | B204: P2006 | C204: 20 | D204: Online | E204: Cash | F204: =VLOOKUP(B204,Catalogue!$A$1:$F$51,5,FALSE) -> 44 | G204: =VLOOKUP(B204,Catalogue!$A$1:$F$51,6,FALSE) -> 72.6 | H204: =C204*F204 -> 880 | I204: =C204*G204 -> 1452 | J204: =I204-H204 -> 572 | K204: Lifebuoy Handwash | L204: =TEXT(A204,"mmm") -> Jul | M204: Personal Care
A205: 45495 | B205: P3002 | C205: 12 | D205: Wholesaler | E205: Online | F205: =VLOOKUP(B205,Catalogue!$A$1:$F$51,5,FALSE) -> 10 | G205: =VLOOKUP(B205,Catalogue!$A$1:$F$51,6,FALSE) -> 11.2 | H205: =C205*F205 -> 120 | I205: =C205*G205 -> 134.4 | J205: =I205-H205 -> 14.4 | K205: Nivea Body Lotion | L205: =TEXT(A205,"mmm") -> Jul | M205: Personal Care
A206: 45496 | B206: P2009 | C206: 12 | D206: Wholesaler | E206: Cash | F206: =VLOOKUP(B206,Catalogue!$A$1:$F$51,5,FALSE) -> 124 | G206: =VLOOKUP(B206,Catalogue!$A$1:$F$51,6,FALSE) -> 167.4 | H206: =C206*F206 -> 1488 | I206: =C206*G206 -> 2008.8 | J206: =I206-H206 -> 520.8 | K206: Gillette Shaving Foam | L206: =TEXT(A206,"mmm") -> Jul | M206: Personal Care
A207: 45497 | B207: P2006 | C207: 12 | D207: Online | E207: Online | F207: =VLOOKUP(B207,Catalogue!$A$1:$F$51,5,FALSE) -> 44 | G207: =VLOOKUP(B207,Catalogue!$A$1:$F$51,6,FALSE) -> 72.6 | H207: =C207*F207 -> 528 | I207: =C207*G207 -> 871.2 | J207: =I207-H207 -> 343.2 | K207: Pantene Shampoo | L207: =TEXT(A207,"mmm") -> Jul | M207: Personal Care
A208: 45498 | B208: P3006 | C208: 14 | D208: Wholesaler | E208: Cash | F208: =VLOOKUP(B208,Catalogue!$A$1:$F$51,5,FALSE) -> 98 | G208: =VLOOKUP(B208,Catalogue!$A$1:$F$51,6,FALSE) -> 161.7 | H208: =C208*F208 -> 1372 | I208: =C208*G208 -> 2263.8 | J208: =I208-H208 -> 891.8 | K208: Dettol Antiseptic Liquid | L208: =TEXT(A208,"mmm") -> Jul | M208: Personal Care
A209: 45499 | B209: P1008 | C209: 10 | D209: Wholesaler | E209: Online | F209: =VLOOKUP(B209,Catalogue!$A$1:$F$51,5,FALSE) -> 16 | G209: =VLOOKUP(B209,Catalogue!$A$1:$F$51,6,FALSE) -> 17.6 | H209: =C209*F209 -> 160 | I209: =C209*G209 -> 176 | J209: =I209-H209 -> 16 | K209: Himalaya Face Wash | L209: =TEXT(A209,"mmm") -> Jul | M209: Personal Care
A210: 45500 | B210: P5005 | C210: 9 | D210: Online | E210: Cash | F210: =VLOOKUP(B210,Catalogue!$A$1:$F$51,5,FALSE) -> 10 | G210: =VLOOKUP(B210,Catalogue!$A$1:$F$51,6,FALSE) -> 14.1 | H210: =C210*F210 -> 90 | I210: =C210*G210 -> 126.9 | J210: =I210-H210 -> 36.9 | K210: Vaseline Lip Care | L210: =TEXT(A210,"mmm") -> Jul | M210: Personal Care
A211: 45501 | B211: P2002 | C211: 9 | D211: Retail Sales | E211: Cash | F211: =VLOOKUP(B211,Catalogue!$A$1:$F$51,5,FALSE) -> 12 | G211: =VLOOKUP(B211,Catalogue!$A$1:$F$51,6,FALSE) -> 13.44 | H211: =C211*F211 -> 108 | I211: =C211*G211 -> 120.96 | J211: =I211-H211 -> 12.96 | K211: Johnson’s Baby Powder | L211: =TEXT(A211,"mmm") -> Jul | M211: Personal Care
A212: 45502 | B212: P5008 | C212: 1 | D212: Retail Sales | E212: Online | F212: =VLOOKUP(B212,Catalogue!$A$1:$F$51,5,FALSE) -> 123 | G212: =VLOOKUP(B212,Catalogue!$A$1:$F$51,6,FALSE) -> 135.3 | H212: =C212*F212 -> 123 | I212: =C212*G212 -> 135.3 | J212: =I212-H212 -> 12.3 | K212: Coca-Cola Can | L212: =TEXT(A212,"mmm") -> Jul | M212: Beverages
A213: 45503 | B213: P3010 | C213: 4 | D213: Online | E213: Cash | F213: =VLOOKUP(B213,Catalogue!$A$1:$F$51,5,FALSE) -> 133 | G213: =VLOOKUP(B213,Catalogue!$A$1:$F$51,6,FALSE) -> 194.18 | H213: =C213*F213 -> 532 | I213: =C213*G213 -> 776.72 | J213: =I213-H213 -> 244.72 | K213: Pepsi Bottle | L213: =TEXT(A213,"mmm") -> Jul | M213: Beverages
A214: 45504 | B214: P1003 | C214: 13 | D214: Wholesaler | E214: Cash | F214: =VLOOKUP(B214,Catalogue!$A$1:$F$51,5,FALSE) -> 44 | G214: =VLOOKUP(B214,Catalogue!$A$1:$F$51,6,FALSE) -> 50.16 | H214: =C214*F214 -> 572 | I214: =C214*G214 -> 652.08 | J214: =I214-H214 -> 80.08 | K214: Red Bull | L214: =TEXT(A214,"mmm") -> Jul | M214: Beverages
... A251: 45541 | B251: P2006 | C251: 17 | D251: Wholesaler | E251: Cash | F251: =VLOOKUP(B251,Catalogue!$A$1:$F$51,5,FALSE) -> 44 | G251: =VLOOKUP(B251,Catalogue!$A$1:$F$51,6,FALSE) -> 72.6 | H251: =C251*F251 -> 748 | I251: =C251*G251 -> 1234.2 | J251: =I251-H251 -> 486.2 | K251: Wet Wipes - Himalaya | L251: =TEXT(A251,"mmm") -> Sep | M251: Paper & Essentials
A252: 45542 | B252: P5008 | C252: 15 | D252: Online | E252: Online | F252: =VLOOKUP(B252,Catalogue!$A$1:$F$51,5,FALSE) -> 123 | G252: =VLOOKUP(B252,Catalogue!$A$1:$F$51,6,FALSE) -> 135.3 | H252: =C252*F252 -> 1845 | I252: =C252*G252 -> 2029.5 | J252: =I252-H252 -> 184.5 | K252: {=Catalogue!B2:B51} -> Dove Soap | L252: =TEXT(A252,"mmm") -> Sep | M252: {=Catalogue!C2:C51} -> Personal Care
A253: 45543 | B253: P4003 | C253: 13 | D253: Wholesaler | E253: Cash | F253: =VLOOKUP(B253,Catalogue!$A$1:$F$51,5,FALSE) -> 16 | G253: =VLOOKUP(B253,Catalogue!$A$1:$F$51,6,FALSE) -> 18.24 | H253: =C253*F253 -> 208 | I253: =C253*G253 -> 237.12 | J253: =I253-H253 -> 29.12 | K253: Colgate Toothpaste | L253: =TEXT(A253,"mmm") -> Sep | M253: Personal Care
A254: 45544 | B254: P1010 | C254: 4 | D254: Wholesaler | E254: Cash | F254: =VLOOKUP(B254,Catalogue!$A$1:$F$51,5,FALSE) -> 123 | G254: =VLOOKUP(B254,Catalogue!$A$1:$F$51,6,FALSE) -> 179.58 | H254: =C254*F254 -> 492 | I254: =C254*G254 -> 718.32 | J254: =I254-H254 -> 226.32 | K254: Lifebuoy Handwash | L254: =TEXT(A254,"mmm") -> Sep | M254: Personal Care
A255: 45545 | B255: P1005 | C255: 17 | D255: Online | E255: Online | F255: =VLOOKUP(B255,Catalogue!$A$1:$F$51,5,FALSE) -> 133 | G255: =VLOOKUP(B255,Catalogue!$A$1:$F$51,6,FALSE) -> 187.53 | H255: =C255*F255 -> 2261 | I255: =C255*G255 -> 3188.01 | J255: =I255-H255 -> 927.01 | K255: Nivea Body Lotion | L255: =TEXT(A255,"mmm") -> Sep | M255: Personal Care
A256: 45546 | B256: P4004 | C256: 7 | D256: Retail Sales | E256: Cash | F256: =VLOOKUP(B256,Catalogue!$A$1:$F$51,5,FALSE) -> 10 | G256: =VLOOKUP(B256,Catalogue!$A$1:$F$51,6,FALSE) -> 11.3 | H256: =C256*F256 -> 70 | I256: =C256*G256 -> 79.1 | J256: =I256-H256 -> 9.1 | K256: Gillette Shaving Foam | L256: =TEXT(A256,"mmm") -> Sep | M256: Personal Care
A257: 45547 | B257: P4002 | C257: 1 | D257: Retail Sales | E257: Online | F257: =VLOOKUP(B257,Catalogue!$A$1:$F$51,5,FALSE) -> 10 | G257: =VLOOKUP(B257,Catalogue!$A$1:$F$51,6,FALSE) -> 11.2 | H257: =C257*F257 -> 10 | I257: =C257*G257 -> 11.2 | J257: =I257-H257 -> 1.2 | K257: Pantene Shampoo | L257: =TEXT(A257,"mmm") -> Sep | M257: Personal Care
A258: 45548 | B258: P1004 | C258: 7 | D258: Online | E258: Cash | F258: =VLOOKUP(B258,Catalogue!$A$1:$F$51,5,FALSE) -> 71 | G258: =VLOOKUP(B258,Catalogue!$A$1:$F$51,6,FALSE) -> 80.23 | H258: =C258*F258 -> 497 | I258: =C258*G258 -> 561.61 | J258: =I258-H258 -> 64.61 | K258: Dettol Antiseptic Liquid | L258: =TEXT(A258,"mmm") -> Sep | M258: Personal Care
A259: 45549 | B259: P2003 | C259: 14 | D259: Wholesaler | E259: Online | F259: =VLOOKUP(B259,Catalogue!$A$1:$F$51,5,FALSE) -> 63 | G259: =VLOOKUP(B259,Catalogue!$A$1:$F$51,6,FALSE) -> 71.82 | H259: =C259*F259 -> 882 | I259: =C259*G259 -> 1005.48 | J259: =I259-H259 -> 123.48 | K259: Himalaya Face Wash | L259: =TEXT(A259,"mmm") -> Sep | M259: Personal Care
A260: 45550 | B260: P1002 | C260: 18 | D260: Wholesaler | E260: Cash | F260: =VLOOKUP(B260,Catalogue!$A$1:$F$51,5,FALSE) -> 105 | G260: =VLOOKUP(B260,Catalogue!$A$1:$F$51,6,FALSE) -> 117.6 | H260: =C260*F260 -> 1890 | I260: =C260*G260 -> 2116.8 | J260: =I260-H260 -> 226.8 | K260: Vaseline Lip Care | L260: =TEXT(A260,"mmm") -> Sep | M260: Personal Care
A261: 45551 | B261: P2005 | C261: 20 | D261: Online | E261: Cash | F261: =VLOOKUP(B261,Catalogue!$A$1:$F$51,5,FALSE) -> 105 | G261: =VLOOKUP(B261,Catalogue!$A$1:$F$51,6,FALSE) -> 148.05 | H261: =C261*F261 -> 2100 | I261: =C261*G261 -> 2961 | J261: =I261-H261 -> 861 | K261: Johnson’s Baby Powder | L261: =TEXT(A261,"mmm") -> Sep | M261: Personal Care
A262: 45552 | B262: P4009 | C262: 16 | D262: Wholesaler | E262: Online | F262: =VLOOKUP(B262,Catalogue!$A$1:$F$51,5,FALSE) -> 98 | G262: =VLOOKUP(B262,Catalogue!$A$1:$F$51,6,FALSE) -> 132.3 | H262: =C262*F262 -> 1568 | I262: =C262*G262 -> 2116.8 | J262: =I262-H262 -> 548.8 | K262: Coca-Cola Can | L262: =TEXT(A262,"mmm") -> Sep | M262: Beverages
A263: 45553 | B263: P4007 | C263: 2 | D263: Wholesaler | E263: Cash | F263: =VLOOKUP(B263,Catalogue!$A$1:$F$51,5,FALSE) -> 12 | G263: =VLOOKUP(B263,Catalogue!$A$1:$F$51,6,FALSE) -> 13.44 | H263: =C263*F263 -> 24 | I263: =C263*G263 -> 26.88 | J263: =I263-H263 -> 2.88 | K263: Pepsi Bottle | L263: =TEXT(A263,"mmm") -> Sep | M263: Beverages
A264: 45554 | B264: P4010 | C264: 15 | D264: Online | E264: Cash | F264: =VLOOKUP(B264,Catalogue!$A$1:$F$51,5,FALSE) -> 105 | G264: =VLOOKUP(B264,Catalogue!$A$1:$F$51,6,FALSE) -> 153.3 | H264: =C264*F264 -> 1575 | I264: =C264*G264 -> 2299.5 | J264: =I264-H264 -> 724.5 | K264: Red Bull | L264: =TEXT(A264,"mmm") -> Sep | M264: Beverages
... A301: 45591 | B301: P4006 | C301: 16 | D301: Retail Sales | E301: Cash | F301: =VLOOKUP(B301,Catalogue!$A$1:$F$51,5,FALSE) -> 136 | G301: =VLOOKUP(B301,Catalogue!$A$1:$F$51,6,FALSE) -> 224.4 | H301: =C301*F301 -> 2176 | I301: =C301*G301 -> 3590.4 | J301: =I301-H301 -> 1414.4 | K301: Wet Wipes - Himalaya | L301: =TEXT(A301,"mmm") -> Oct | M301: Paper & Essentials
A302: 45592 | B302: P1008 | C302: 3 | D302: Retail Sales | E302: Online | F302: =VLOOKUP(B302,Catalogue!$A$1:$F$51,5,FALSE) -> 16 | G302: =VLOOKUP(B302,Catalogue!$A$1:$F$51,6,FALSE) -> 17.6 | H302: =C302*F302 -> 48 | I302: =C302*G302 -> 52.8 | J302: =I302-H302 -> 4.8 | K302: {=Catalogue!B2:B51} -> Dove Soap | L302: =TEXT(A302,"mmm") -> Oct | M302: {=Catalogue!C2:C51} -> Personal Care
A303: 45593 | B303: P1001 | C303: 16 | D303: Online | E303: Cash | F303: =VLOOKUP(B303,Catalogue!$A$1:$F$51,5,FALSE) -> 98 | G303: =VLOOKUP(B303,Catalogue!$A$1:$F$51,6,FALSE) -> 129.36 | H303: =C303*F303 -> 1568 | I303: =C303*G303 -> 2069.76 | J303: =I303-H303 -> 501.76 | K303: Colgate Toothpaste | L303: =TEXT(A303,"mmm") -> Oct | M303: Personal Care
A304: 45594 | B304: P2009 | C304: 2 | D304: Wholesaler | E304: Cash | F304: =VLOOKUP(B304,Catalogue!$A$1:$F$51,5,FALSE) -> 124 | G304: =VLOOKUP(B304,Catalogue!$A$1:$F$51,6,FALSE) -> 167.4 | H304: =C304*F304 -> 248 | I304: =C304*G304 -> 334.8 | J304: =I304-H304 -> 86.8 | K304: Lifebuoy Handwash | L304: =TEXT(A304,"mmm") -> Oct | M304: Personal Care
A305: 45595 | B305: P4010 | C305: 19 | D305: Wholesaler | E305: Online | F305: =VLOOKUP(B305,Catalogue!$A$1:$F$51,5,FALSE) -> 105 | G305: =VLOOKUP(B305,Catalogue!$A$1:$F$51,6,FALSE) -> 153.3 | H305: =C305*F305 -> 1995 | I305: =C305*G305 -> 2912.7 | J305: =I305-H305 -> 917.7 | K305: Nivea Body Lotion | L305: =TEXT(A305,"mmm") -> Oct | M305: Personal Care
A306: 45596 | B306: P5008 | C306: 19 | D306: Online | E306: Cash | F306: =VLOOKUP(B306,Catalogue!$A$1:$F$51,5,FALSE) -> 123 | G306: =VLOOKUP(B306,Catalogue!$A$1:$F$51,6,FALSE) -> 135.3 | H306: =C306*F306 -> 2337 | I306: =C306*G306 -> 2570.7 | J306: =I306-H306 -> 233.7 | K306: Gillette Shaving Foam | L306: =TEXT(A306,"mmm") -> Oct | M306: Personal Care
A307: 45597 | B307: P3004 | C307: 11 | D307: Wholesaler | E307: Online | F307: =VLOOKUP(B307,Catalogue!$A$1:$F$51,5,FALSE) -> 136 | G307: =VLOOKUP(B307,Catalogue!$A$1:$F$51,6,FALSE) -> 153.68 | H307: =C307*F307 -> 1496 | I307: =C307*G307 -> 1690.48 | J307: =I307-H307 -> 194.48 | K307: Pantene Shampoo | L307: =TEXT(A307,"mmm") -> Nov | M307: Personal Care
A308: 45598 | B308: P2010 | C308: 3 | D308: Wholesaler | E308: Cash | F308: =VLOOKUP(B308,Catalogue!$A$1:$F$51,5,FALSE) -> 10 | G308: =VLOOKUP(B308,Catalogue!$A$1:$F$51,6,FALSE) -> 14.6 | H308: =C308*F308 -> 30 | I308: =C308*G308 -> 43.8 | J308: =I308-H308 -> 13.8 | K308: Dettol Antiseptic Liquid | L308: =TEXT(A308,"mmm") -> Nov | M308: Personal Care
A309: 45599 | B309: P5004 | C309: 10 | D309: Online | E309: Online | F309: =VLOOKUP(B309,Catalogue!$A$1:$F$51,5,FALSE) -> 124 | G309: =VLOOKUP(B309,Catalogue!$A$1:$F$51,6,FALSE) -> 140.12 | H309: =C309*F309 -> 1240 | I309: =C309*G309 -> 1401.2 | J309: =I309-H309 -> 161.2 | K309: Himalaya Face Wash | L309: =TEXT(A309,"mmm") -> Nov | M309: Personal Care
A310: 45600 | B310: P4008 | C310: 19 | D310: Retail Sales | E310: Cash | F310: =VLOOKUP(B310,Catalogue!$A$1:$F$51,5,FALSE) -> 63 | G310: =VLOOKUP(B310,Catalogue!$A$1:$F$51,6,FALSE) -> 69.3 | H310: =C310*F310 -> 1197 | I310: =C310*G310 -> 1316.7 | J310: =I310-H310 -> 119.7 | K310: Vaseline Lip Care | L310: =TEXT(A310,"mmm") -> Nov | M310: Personal Care
A311: 45601 | B311: P2008 | C311: 14 | D311: Retail Sales | E311: Cash | F311: =VLOOKUP(B311,Catalogue!$A$1:$F$51,5,FALSE) -> 133 | G311: =VLOOKUP(B311,Catalogue!$A$1:$F$51,6,FALSE) -> 146.3 | H311: =C311*F311 -> 1862 | I311: =C311*G311 -> 2048.2 | J311: =I311-H311 -> 186.2 | K311: Johnson’s Baby Powder | L311: =TEXT(A311,"mmm") -> Nov | M311: Personal Care
A312: 45602 | B312: P1002 | C312: 17 | D312: Online | E312: Online | F312: =VLOOKUP(B312,Catalogue!$A$1:$F$51,5,FALSE) -> 105 | G312: =VLOOKUP(B312,Catalogue!$A$1:$F$51,6,FALSE) -> 117.6 | H312: =C312*F312 -> 1785 | I312: =C312*G312 -> 1999.2 | J312: =I312-H312 -> 214.2 | K312: Coca-Cola Can | L312: =TEXT(A312,"mmm") -> Nov | M312: Beverages
A313: 45603 | B313: P4008 | C313: 1 | D313: Wholesaler | E313: Cash | F313: =VLOOKUP(B313,Catalogue!$A$1:$F$51,5,FALSE) -> 63 | G313: =VLOOKUP(B313,Catalogue!$A$1:$F$51,6,FALSE) -> 69.3 | H313: =C313*F313 -> 63 | I313: =C313*G313 -> 69.3 | J313: =I313-H313 -> 6.3 | K313: Pepsi Bottle | L313: =TEXT(A313,"mmm") -> Nov | M313: Beverages
A314: 45604 | B314: P2005 | C314: 12 | D314: Wholesaler | E314: Cash | F314: =VLOOKUP(B314,Catalogue!$A$1:$F$51,5,FALSE) -> 105 | G314: =VLOOKUP(B314,Catalogue!$A$1:$F$51,6,FALSE) -> 148.05 | H314: =C314*F314 -> 1260 | I314: =C314*G314 -> 1776.6 | J314: =I314-H314 -> 516.6 | K314: Red Bull | L314: =TEXT(A314,"mmm") -> Nov | M314: Beverages
... A351: 45641 | B351: P1004 | C351: 10 | D351: Online | E351: Cash | F351: =VLOOKUP(B351,Catalogue!$A$1:$F$51,5,FALSE) -> 71 | G351: =VLOOKUP(B351,Catalogue!$A$1:$F$51,6,FALSE) -> 80.23 | H351: =C351*F351 -> 710 | I351: =C351*G351 -> 802.3 | J351: =I351-H351 -> 92.3 | K351: Wet Wipes - Himalaya | L351: =TEXT(A351,"mmm") -> Dec | M351: Paper & Essentials
A352: 45642 | B352: P2007 | C352: 20 | D352: Wholesaler | E352: Online | F352: =VLOOKUP(B352,Catalogue!$A$1:$F$51,5,FALSE) -> 71 | G352: =VLOOKUP(B352,Catalogue!$A$1:$F$51,6,FALSE) -> 79.52 | H352: =C352*F352 -> 1420 | I352: =C352*G352 -> 1590.4 | J352: =I352-H352 -> 170.4 | K352: {=Catalogue!B2:B51} -> Dove Soap | L352: =TEXT(A352,"mmm") -> Dec | M352: {=Catalogue!C2:C51} -> Personal Care
...
